pybughunt/__init__.py
pybughunt/__main__.py
pybughunt/cli.py
pybughunt/detector.py
pybughunt/driver.py
pybughunt/logic_analyzer.py
pybughunt/sample_buggy.py
pybughunt/syntax_analyzer.py
pybughunt/utils.py
"pybughunt/models/__init__,py"
pybughunt/models/model_loader.py
pybughunt/models/model_trainer.py
pybughunt-0.2.0.dist-info/licenses/LICENSE
pybughunt-0.2.0.dist-info/METADATA
pybughunt-0.2.0.dist-info/WHEEL
pybughunt-0.2.0.dist-info/top_level.txt
pybughunt-0.2.0.dist-info/RECORD
