Metadata-Version: 2.4
Name: pybughunt
Version: 0.2.0
Summary: A Python library for detecting logical and syntactical errors in Python code
Home-page: https://github.com/Preksha-7/pybughunt
Author: Preksha Upadhyay
Author-email: Preksha Upadhyay <prekshaupadhyay03@gmail.com>
License: MIT
Keywords: code,python,error,detection,static analysis
Classifier: Development Status :: 3 - Alpha
Classifier: Intended Audience :: Developers
Classifier: Programming Language :: Python :: 3
Classifier: Programming Language :: Python :: 3.8
Classifier: Programming Language :: Python :: 3.9
Requires-Python: >=3.8
License-File: LICENSE
Requires-Dist: numpy>=1.20.0
Requires-Dist: scikit-learn>=1.0.0
Requires-Dist: torch>=1.9.0
Requires-Dist: transformers>=4.12.0
Requires-Dist: astroid>=2.8.0
Requires-Dist: pylint>=2.11.0
Dynamic: author
Dynamic: home-page
Dynamic: license-file
Dynamic: requires-python
